FancyLogger/__init__.py
FancyLogger/colors.py
FancyLogger/extra.py
FancyLogger/logger.py
pyfancylogger-0.3.2.dist-info/LICENSE.md
pyfancylogger-0.3.2.dist-info/METADATA
pyfancylogger-0.3.2.dist-info/WHEEL
pyfancylogger-0.3.2.dist-info/top_level.txt
pyfancylogger-0.3.2.dist-info/RECORD
