Metadata-Version: 2.1
Name: pyfancylogger
Version: 0.3.2
Summary: A Fast & Fancy version of logging
Author-email: Ashenguard <ashenguard@agmstudio.xyz>
Project-URL: Homepage, https://github.com/agm-studio/fancylogger
Project-URL: Bug Tracker, https://github.com/agm-studio/fancylogger/issues
Classifier: Programming Language :: Python :: 3
Classifier: License :: OSI Approved :: MIT License
Classifier: Development Status :: 4 - Beta
Classifier: Operating System :: OS Independent
Requires-Python: >=3.9
License-File: LICENSE.md
Requires-Dist: deprecated
